whatnow/__init__.py
whatnow/what.py
whatnow-0.1.3.dist-info/LICENSE
whatnow-0.1.3.dist-info/METADATA
whatnow-0.1.3.dist-info/WHEEL
whatnow-0.1.3.dist-info/top_level.txt
whatnow-0.1.3.dist-info/RECORD
