Metadata-Version: 2.1
Name: whatnow
Version: 0.1.3
Summary: A module to get the the current Day, Date, Time and Temperature
Home-page: https://github.com/inspironman/whatnow
Author: Deepak Kumar Upadhayay
Author-email: dku3132@gmail.com
Classifier: Programming Language :: Python :: 3
Classifier: License :: OSI Approved :: MIT License
Classifier: Operating System :: OS Independent
Requires-Python: >=3.6
License-File: LICENSE
